baikal/__init__.py
baikal/_version.py
baikal/plot.py
baikal/sklearn.py
baikal/_core/__init__.py
baikal/_core/config.py
baikal/_core/data_placeholder.py
baikal/_core/digraph.py
baikal/_core/model.py
baikal/_core/pprint.py
baikal/_core/step.py
baikal/_core/typing.py
baikal/_core/utils.py
baikal/steps/__init__.py
baikal/steps/expression.py
baikal/steps/factory.py
baikal/steps/merge.py
baikal-0.4.2.dist-info/LICENSE
baikal-0.4.2.dist-info/METADATA
baikal-0.4.2.dist-info/WHEEL
baikal-0.4.2.dist-info/top_level.txt
baikal-0.4.2.dist-info/RECORD
