Metadata-Version: 2.1
Name: baikal
Version: 0.4.2
Summary: A graph-based functional API for building complex scikit-learn pipelines.
Home-page: https://github.com/alegonz/baikal
Author: Alejandro González Tineo
Author-email: alejandrojgt@gmail.com
License: new BSD
Platform: UNKNOWN
Classifier: Development Status :: 3 - Alpha
Classifier: Intended Audience :: Science/Research
Classifier: Intended Audience :: Developers
Classifier: License :: OSI Approved :: BSD License
Classifier: Topic :: Software Development
Classifier: Topic :: Scientific/Engineering
Classifier: Programming Language :: Python
Classifier: Programming Language :: Python :: 3
Classifier: Programming Language :: Python :: 3.5
Classifier: Programming Language :: Python :: 3.6
Classifier: Programming Language :: Python :: 3.7
Requires-Python: >=3.5
Requires-Dist: numpy
Provides-Extra: dev
Requires-Dist: codecov ; extra == 'dev'
Requires-Dist: joblib ; extra == 'dev'
Requires-Dist: mypy ; extra == 'dev'
Requires-Dist: pytest ; extra == 'dev'
Requires-Dist: pytest-cov ; extra == 'dev'
Requires-Dist: scikit-learn ; extra == 'dev'
Provides-Extra: viz
Requires-Dist: pydot ; extra == 'viz'
